README.md
setup.cfg
setup.py
projectZ/__init__.py
projectZ/async_client.py
projectZ/async_socket.py
projectZ/client.py
projectZ/socket.py
projectZ.py.egg-info/PKG-INFO
projectZ.py.egg-info/SOURCES.txt
projectZ.py.egg-info/dependency_links.txt
projectZ.py.egg-info/requires.txt
projectZ.py.egg-info/top_level.txt
projectZ/utils/__init__.py
projectZ/utils/exceptions.py
projectZ/utils/generator.py
projectZ/utils/headers.py
projectZ/utils/objects.py