Metadata-Version: 2.1
Name: projectZ.py
Version: 1.1.6.7
Summary: Library for creating projectZ bots and scripts.
Home-page: https://github.com/xXxCLOTIxXx/projectZ.py
Author: Xsarz
Author-email: xsarzy@gmail.com
License: MIT
Download-URL: https://github.com/xXxCLOTIxXx/projectZ.py/archive/refs/heads/main.zip
Keywords: projectZ.py,projectZ,projectZ-py,projectZ-bot,api,python,python3,python3.x,xsarz,official,async,sync
Platform: UNKNOWN
